names/__init__.py
names/__main__.py
names/abbreviate.py
abbreviate_names-0.1.2.dist-info/LICENCE.md
abbreviate_names-0.1.2.dist-info/METADATA
abbreviate_names-0.1.2.dist-info/WHEEL
abbreviate_names-0.1.2.dist-info/entry_points.txt
abbreviate_names-0.1.2.dist-info/top_level.txt
abbreviate_names-0.1.2.dist-info/RECORD
