Metadata-Version: 2.1
Name: abbreviate-names
Version: 0.1.2
Summary: Uniquely abbreviate a set of names in a language-appropriate way.
Home-page: https://github.com/ConradHughes/abbreviate-names
Author: Conrad Hughes
Author-email: h_d24e0f27c082b3eb54c1@xrad.org
License: AGPL-3.0+
Keywords: abbreviate,names,latin,english
Platform: UNKNOWN
Classifier: Programming Language :: Python :: 3
Classifier: License :: OSI Approved :: GNU Affero General Public License v3 or later (AGPLv3+)
Classifier: Operating System :: OS Independent
Classifier: Topic :: Text Processing :: Linguistic
Classifier: Topic :: Utilities
Requires-Python: >=3.6
Provides-Extra: english
Requires-Dist: nltk (>=3.5) ; extra == 'english'
Provides-Extra: latin
Requires-Dist: cltk (>=0.1.121) ; extra == 'latin'
